mcp_server_opensearch/__init__.py
mcp_server_opensearch/__main__.py
mcp_server_opensearch/sse_server.py
mcp_server_opensearch/stdio_server.py
opensearch/__init__.py
opensearch/client.py
opensearch/helper.py
test_mcp_opensearch-0.1.0.dist-info/licenses/LICENSE
tools/__init__.py
tools/tools.py
test_mcp_opensearch-0.1.0.dist-info/METADATA
test_mcp_opensearch-0.1.0.dist-info/WHEEL
test_mcp_opensearch-0.1.0.dist-info/entry_points.txt
test_mcp_opensearch-0.1.0.dist-info/top_level.txt
test_mcp_opensearch-0.1.0.dist-info/RECORD
