Metadata-Version: 2.4
Name: test-mcp-opensearch
Version: 0.1.0
Summary: Add your description here
Requires-Python: >=3.10
License-File: LICENSE
Requires-Dist: boto3>=1.38.3
Requires-Dist: mcp[cli]>=1.6.0
Requires-Dist: opensearch-py>=2.8.0
Requires-Dist: pydantic>=2.11.3
Requires-Dist: pytest>=8.3.5
Requires-Dist: pytest-asyncio>=0.26.0
Requires-Dist: requests-aws4auth>=1.3.1
Dynamic: license-file
